envppp-0.1.1.dist-info/METADATA
envppp-0.1.1.dist-info/WHEEL
main.py
envppp-0.1.1.dist-info/RECORD
