Metadata-Version: 2.1
Name: envppp
Version: 0.1.1
Summary: Uma cli para criar projetos em python, javascript e C++
Author: Every
Project-URL: Repository, https://github.com/Every2/envpp
Requires-Python: >=3.11
Requires-Dist: typer[all]>=0.9.0
